RTL-designs/Design_16/seven_segments/src/seven_segments.sv
module seven_segments
(
input  logic [3:0] data,
output logic [6:0] segments
);
always_comb
    case(data)
    // abc_defg
        0: segments = 7'b111_1110;
        1: segments = 7'b011_0000;
        2: segments = 7'b110_1101;
        3: segments = 7'b111_1001;
        4: segments = 7'b011_0011;
        5: segments = 7'b101_1011;
        6: segments = 7'b101_1111;
        7: segments = 7'b111_0000;
        8: segments = 7'b111_1111;
        9: segments = 7'b111_0011;
        default: segments = 7'b000_0000;
    endcase
endmodule

RTL-designs/Design_16/seven_segments/waveform.vcd
$version Generated by VerilatedVcd $end
$date Tue Apr 16 03:27:53 2024
 $end
$timescale   1ps $end

 $scope module TOP $end
  $var wire  4 # data [3:0] $end
  $var wire  7 $ segments [6:0] $end
  $scope module seven_segments $end
   $var wire  4 # data [3:0] $end
   $var wire  7 $ segments [6:0] $end
  $upscope $end
 $upscope $end
$enddefinitions $end


#0
b0000 #
b1111110 $
#1
#2
b0001 #
b0110000 $
#3
#4
b0010 #
b1101101 $
#5
#6
b0011 #
b1111001 $
#7
#8
b0100 #
b0110011 $
#9
#10
b0101 #
b1011011 $
#11
#12
b0110 #
b1011111 $
#13
#14
b0111 #
b1110000 $
#15
#16
b1000 #
b1111111 $
#17
#18
b1001 #
b1110011 $
